pyregf.cp312-win32.pyd
libregf_python-20240421.dist-info/METADATA
libregf_python-20240421.dist-info/WHEEL
libregf_python-20240421.dist-info/top_level.txt
libregf_python-20240421.dist-info/RECORD
